{
  "formdetails": [
    {
      "firstName": "Anindit",
      "lastName": "Panigrahi",
      "id": "3d30465e-65d0-8792-ec22-14482e469338"
    },
    {
      "firstName": "Naveen",
      "lastName": "gayar",
      "id": "97d99416-75d8-b15d-97df-4ad5099d9a43"
    },
    {
      "id": "c0c73de9-8209-dc09-e951-b0193251d777",
      "firstName": "Nishad",
      "lastName": "Alam"
    },
    {
      "id": "5e46b2b6-cd3d-4cec-d20d-b7d61811413a",
      "firstName": "Daksh",
      "lastName": "Patel"
    }
  ]
}